Pratica 2025.2 U2C2/mux/multiplexador.v
module multiplexador (e1, e2, e3, e4, s0, s1, x);
input e1, e2, e3, e4, s0, s1;
output x;

assign x = ~s0 & ~s1 & e1 | s0 & ~s1 & e2 | ~s0 & s1 & e3 | s0 & s1 & e4;
endmodule

Pratica 2025.2 U2C2/mux/multiplexador_tb.v
`include "multiplexador.v"
`timescale 1ns/100ps

module multiplexador_tb;
reg e1, e2, e3, e4, s0, s1;
wire x;

multiplexador uut (.e1(e1), .e2(e2), .e3(e3), .e4(e4), .s0(s0), .s1(s1), .x(x));

initial begin
    $dumpfile("multiplexador.vcd");
    $dumpvars(0, multiplexador_tb);
    s1 = 0; s0 = 0; e1 = 0; e2 = 0; e3 = 0; e4 = 0; #10;
    for (integer i = 0; i < 64; i++) begin
        {s1, s0, e1, e2, e3, e4} = i+1;
        #10;
    end

end
endmodule

Pratica 2025.2 U2C2/mux/multiplexador.vcd
$date
	Thu Aug 21 11:16:48 2025
$end
$version
	Icarus Verilog
$end
$timescale
	100ps
$end
$scope module multiplexador_tb $end
$var wire 1 ! x $end
$var reg 1 " e1 $end
$var reg 1 # e2 $end
$var reg 1 $ e3 $end
$var reg 1 % e4 $end
$var reg 1 & s0 $end
$var reg 1 ' s1 $end
$scope module uut $end
$var wire 1 " e1 $end
$var wire 1 # e2 $end
$var wire 1 $ e3 $end
$var wire 1 % e4 $end
$var wire 1 & s0 $end
$var wire 1 ' s1 $end
$var wire 1 ! x $end
$upscope $end
$scope begin $ivl_for_loop0 $end
$var integer 32 ( i [31:0] $end
$upscope $end
$upscope $end
$enddefinitions $end
$comment Show the parameter values. $end
$dumpall
$end
#0
$dumpvars
bx (
0'
0&
0%
0$
0#
0"
0!
$end
#100
1%
b0 (
#200
1$
0%
b1 (
#300
1%
b10 (
#400
1#
0$
0%
b11 (
#500
1%
b100 (
#600
1$
0%
b101 (
#700
1%
b110 (
#800
1!
1"
0#
0$
0%
b111 (
#900
1%
b1000 (
#1000
1$
0%
b1001 (
#1100
1%
b1010 (
#1200
1#
0$
0%
b1011 (
#1300
1%
b1100 (
#1400
1$
0%
b1101 (
#1500
1%
b1110 (
#1600
0!
1&
0"
0#
0$
0%
b1111 (
#1700
1%
b10000 (
#1800
1$
0%
b10001 (
#1900
1%
b10010 (
#2000
1!
1#
0$
0%
b10011 (
#2100
1%
b10100 (
#2200
1$
0%
b10101 (
#2300
1%
b10110 (
#2400
0!
1"
0#
0$
0%
b10111 (
#2500
1%
b11000 (
#2600
1$
0%
b11001 (
#2700
1%
b11010 (
#2800
1!
1#
0$
0%
b11011 (
#2900
1%
b11100 (
#3000
1$
0%
b11101 (
#3100
1%
b11110 (
#3200
0!
1'
0&
0"
0#
0$
0%
b11111 (
#3300
1%
b100000 (
#3400
1!
1$
0%
b100001 (
#3500
1%
b100010 (
#3600
0!
1#
0$
0%
b100011 (
#3700
1%
b100100 (
#3800
1!
1$
0%
b100101 (
#3900
1%
b100110 (
#4000
0!
1"
0#
0$
0%
b100111 (
#4100
1%
b101000 (
#4200
1!
1$
0%
b101001 (
#4300
1%
b101010 (
#4400
0!
1#
0$
0%
b101011 (
#4500
1%
b101100 (
#4600
1!
1$
0%
b101101 (
#4700
1%
b101110 (
#4800
0!
1&
0"
0#
0$
0%
b101111 (
#4900
1!
1%
b110000 (
#5000
0!
1$
0%
b110001 (
#5100
1!
1%
b110010 (
#5200
0!
1#
0$
0%
b110011 (
#5300
1!
1%
b110100 (
#5400
0!
1$
0%
b110101 (
#5500
1!
1%
b110110 (
#5600
0!
1"
0#
0$
0%
b110111 (
#5700
1!
1%
b111000 (
#5800
0!
1$
0%
b111001 (
#5900
1!
1%
b111010 (
#6000
0!
1#
0$
0%
b111011 (
#6100
1!
1%
b111100 (
#6200
0!
1$
0%
b111101 (
#6300
1!
1%
b111110 (
#6400
0!
0'
0&
0"
0#
0$
0%
b111111 (
#6500
b1000000 (
