Pratica 2025.2 U2C2/paridade_par/paridade_par.v
module paridade_par (a, b, c, s);
input a, b, c;
output s;

assign s = ~(a ^ b) ^ c;
endmodule

Pratica 2025.2 U2C2/paridade_par/paridade_par_tb.v
`include "paridade_par.v"
`timescale 1ns/100ps

module paridade_par_tb;
reg a0, b0, c0;
wire s0;

paridade_par uut (.a(a0), .b(b0), .c(c0), .s(s0));

initial begin
    $dumpfile("paridade_par.vcd");
    $dumpvars(0, paridade_par_tb);
    a0 = 0; b0 = 0; c0 = 0; 
    #10; a0 = 0; b0 = 0; c0 = 1;
    #10; a0 = 0; b0 = 1; c0 = 0;
    #10; a0 = 0; b0 = 1; c0 = 1;
    #10; a0 = 1; b0 = 0; c0 = 0;
    #10; a0 = 1; b0 = 0; c0 = 1;
    #10; a0 = 1; b0 = 1; c0 = 0;
    #10; a0 = 1; b0 = 1; c0 = 1;
    #10; $finish;
end
endmodule

Pratica 2025.2 U2C2/paridade_par/paridade_par.vcd
$date
	Tue Aug 19 11:58:32 2025
$end
$version
	Icarus Verilog
$end
$timescale
	100ps
$end
$scope module paridade_par_tb $end
$var wire 1 ! s0 $end
$var reg 1 " a0 $end
$var reg 1 # b0 $end
$var reg 1 $ c0 $end
$scope module uut $end
$var wire 1 " a $end
$var wire 1 # b $end
$var wire 1 $ c $end
$var wire 1 ! s $end
$upscope $end
$upscope $end
$enddefinitions $end
$comment Show the parameter values. $end
$dumpall
$end
#0
$dumpvars
0$
0#
0"
1!
$end
#100
0!
1$
#200
0!
0$
1#
#300
1!
1$
#400
0!
0$
0#
1"
#500
1!
1$
#600
1!
0$
1#
#700
0!
1$
