Pratica 2025.2 U2C2/codificador4/codificador.v
module codificador (e1, e2, e3, s0, s1);
input e1, e2, e3;
output s0, s1;

wire xor123;
assign xor123 = e1 ^ e2 ^ e3 & ~(e1 & e2 & e3);

assign s0 = (e2 | e3) & xor123;
assign s1 = (e1 | e3) & xor123;
endmodule

Pratica 2025.2 U2C2/codificador16/codificador_tb.v
`include "codificador.v"
`timescale 1ns/100ps

module codificador_tb;
reg e1, e2, e3;
wire s0, s1;

codificador uut (.e1(e1), .e2(e2), .e3(e3), .s0(s0), .s1(s1));

initial begin
    $dumpfile("codificador.vcd");
    $dumpvars(0, codificador_tb);
    e1 = 0; e2 = 0; e3 = 0; #10;
    e1 = 0; e2 = 0; e3 = 1; #10;
    e1 = 0; e2 = 1; e3 = 0; #10;
    e1 = 0; e2 = 1; e3 = 1; #10;
    e1 = 1; e2 = 0; e3 = 0; #10;
    e1 = 1; e2 = 0; e3 = 1; #10;
    e1 = 1; e2 = 1; e3 = 0; #10;
    e1 = 1; e2 = 1; e3 = 1; #10;
end
endmodule

Pratica 2025.2 U2C2/codificador4/codificador.vcd
$date
	Thu Aug 21 09:17:59 2025
$end
$version
	Icarus Verilog
$end
$timescale
	100ps
$end
$scope module codificador_tb $end
$var wire 1 ! s1 $end
$var wire 1 " s0 $end
$var reg 1 # e1 $end
$var reg 1 $ e2 $end
$var reg 1 % e3 $end
$scope module uut $end
$var wire 1 # e1 $end
$var wire 1 $ e2 $end
$var wire 1 % e3 $end
$var wire 1 " s0 $end
$var wire 1 ! s1 $end
$var wire 1 & xor123 $end
$upscope $end
$upscope $end
$enddefinitions $end
$comment Show the parameter values. $end
$dumpall
$end
#0
$dumpvars
0&
0%
0$
0#
0"
0!
$end
#100
1"
1!
1&
1%
#200
0!
0%
1$
#300
0"
0&
1%
#400
1!
1&
0%
0$
1#
#500
0!
0&
1%
#600
0%
1$
#700
1"
1!
1&
1%
